{
  "background": [
    {
      "id": 1,
      "type": "background1",
      "title": "icon",
      "img": "global/assets/background/stamp-bg-4.png",
      "fullImg": "global/assets/background/full_bg_4.jpg",
      "format": ".png",
      "active": "false"
    },
    {
      "id": 2,
      "type": "background2",
      "title": "icon",
      "img": "global/assets/background/stamp-bg-5.png",
      "fullImg": "global/assets/background/full_bg_5.jpg",
      "format": ".png",
      "active": "false"
    },
    {
      "id": 3,
      "type": "background3",
      "title": "icon",
      "img": "global/assets/background/stamp-bg-6.png",
      "fullImg": "global/assets/background/full_bg_6.jpg",
      "format": ".png",
      "active": "false"
    }
  ],
  "giftBox": [
    {
      "id": 1,
      "type": "state1",
      "title": "icon",
      "img": "global/assets/game/gift1.png",
      "fullImg": "global/assets/game/gift1.png",
      "format": ".png",
      "active": "false"
    },
    {
      "id": 2,
      "type": "state2",
      "title": "icon",
      "img": "global/assets/game/gift2.png",
      "fullImg": "global/assets/game/gift2.png",
      "format": ".png",
      "active": "false"
    },
    {
      "id": 3,
      "type": "state3",
      "title": "icon",
      "img": "global/assets/game/gift3.png",
      "fullImg": "global/assets/game/gift3.png",
      "format": ".png",
      "active": "false"
    }
  ],
  "gamesTree": [
    {
      "id": 1,
      "type": "simple-tree",
      "active": "false",
      "img": "global/assets/game/mini_tree_1.png",
      "fullImg": "global/assets/game/full_tree_1.png",
      "title": "tree"
    },
    {
      "id": 2,
      "type": "fir-tree",
      "active": "false",
      "img": "global/assets/game/mini_tree_2.png",
      "fullImg": "global/assets/game/full_tree_2.png",
      "title": "fir tree"
    },
    {
      "id": 3,
      "type": "tree-pot",
      "active": "false",
      "img": "global/assets/game/mini_tree_3.png",
      "fullImg": "global/assets/game/full_tree_3.png",
      "title": "tree in a pot"
    }
  ],
  "gameNumberGift": [
    {
      "value": 3,
      "viewValue": "3"
    },
    {
      "value": 4,
      "viewValue": "4"
    },
    {
      "value": 5,
      "viewValue": "5"
    },
    {
      "value": 6,
      "viewValue": "6"
    },
    {
      "value": 7,
      "viewValue": "7"
    },
    {
      "value": 8,
      "viewValue": "8"
    },
    {
      "value": 9,
      "viewValue": "9"
    }
  ]
}
