[
  {
    "id": 2,
    "type": "shake",
    "title": "SHAKE_THE_TREE",
    "img": "assets/images/games/shake.png",
    "active": "false"
  },
  {
    "id": 3,
    "type": "tap",
    "title": "HIT_THE_PINATA",
    "img": "assets/images/games/tap.png",
    "active": "false"
  },
  {
    "id": 5,
    "type": "scratch",
    "title": "SCRATCH_THE_CARD",
    "img": "assets/images/games/scratch.png",
    "active": "false"
  },
  {
    "id": 6,
    "type": "spin",
    "title": "SPIN_THE_WHEEL",
    "img": "assets/images/games/spinTheWheel.png",
    "active": "false"
  },
  {
    "id": 7,
    "type": "snake",
    "title": "PLAY_SNAKE",
    "img": "assets/images/games/snake.png",
    "active": "false"
  }
]
